topqad_sdk/__init__.py
topqad_sdk/_exceptions.py
topqad_sdk/_utils.py
topqad_sdk/_auth/__init__.py
topqad_sdk/_auth/_auth_manager.py
topqad_sdk/_http_request/__init__.py
topqad_sdk/_http_request/_http_client.py
topqad_sdk/clients/__init__.py
topqad_sdk/clients/_topqad_client.py
topqad_sdk/clients/compiler_client.py
topqad_sdk/clients/noise_profiler_client.py
topqad_sdk/clients/qre_client.py
topqad_sdk/compiler/__init__.py
topqad_sdk/compiler/compiler.py
topqad_sdk/library/__init__.py
topqad_sdk/library/circuit_library.py
topqad_sdk/library/hardware_parameter_library.py
topqad_sdk/models/__init__.py
topqad_sdk/models/common_types.py
topqad_sdk/models/enums.py
topqad_sdk/models/assembler/__init__.py
topqad_sdk/models/assembler/assembler_reports.py
topqad_sdk/models/assembler/responses.py
topqad_sdk/models/circuit_library/__init__.py
topqad_sdk/models/circuit_library/circuit.py
topqad_sdk/models/circuit_library/response.py
topqad_sdk/models/compiler/__init__.py
topqad_sdk/models/compiler/requests.py
topqad_sdk/models/compiler/responses.py
topqad_sdk/models/decomposer/__init__.py
topqad_sdk/models/decomposer/responses.py
topqad_sdk/models/noise_profiler/__init__.py
topqad_sdk/models/noise_profiler/requests.py
topqad_sdk/models/noise_profiler/responses.py
topqad_sdk/models/optimizer/__init__.py
topqad_sdk/models/optimizer/responses.py
topqad_sdk/models/pipeline/__init__.py
topqad_sdk/models/pipeline/requests.py
topqad_sdk/models/pipeline/responses.py
topqad_sdk/models/scheduler/__init__.py
topqad_sdk/models/scheduler/responses.py
topqad_sdk/noiseprofiler/__init__.py
topqad_sdk/noiseprofiler/fit.py
topqad_sdk/noiseprofiler/models.py
topqad_sdk/noiseprofiler/qre_noiseprofile.py
topqad_sdk/noiseprofiler/simtable.py
topqad_sdk/noiseprofiler/data/__init__.py
topqad_sdk/noiseprofiler/data/qre_presets/__init__.py
topqad_sdk/noiseprofiler/data/qre_presets/physical_depolarizing_baseline.json
topqad_sdk-0.4.0.dist-info/licenses/LICENSE
topqad_sdk-0.4.0.dist-info/METADATA
topqad_sdk-0.4.0.dist-info/WHEEL
topqad_sdk-0.4.0.dist-info/top_level.txt
topqad_sdk-0.4.0.dist-info/RECORD
