Metadata-Version: 2.4
Name: topqad-sdk
Version: 0.4.0
Summary: SDK for TopQAD
Author-email: 1QBit <topqad.support@1qbit.com>
License:                                  Apache License
Project-URL: Homepage, https://topqad.1qbit.com
Project-URL: Documentation, https://1qb-information-technologies.github.io/topqad-sdk-for-python/api/topqad_sdk.html
Keywords: quantum,resource,estimation
Classifier: Programming Language :: Python :: 3
Classifier: Operating System :: OS Independent
Requires-Python: >=3.10
License-File: LICENSE
Requires-Dist: PyJWT~=2.10
Requires-Dist: pydantic~=2.11
Requires-Dist: python-dotenv~=1.1
Requires-Dist: httpx~=0.28
Requires-Dist: uncertainties~=3.2
Requires-Dist: matplotlib<=3.10.3,>=3.8
Requires-Dist: scipy<=1.15.3,>=1.12
Requires-Dist: tabulate~=0.9
Requires-Dist: sympy~=1.13
Requires-Dist: notebook~=7.4
Requires-Dist: pandas~=2.2
Requires-Dist: Jinja2~=3.1
Requires-Dist: sinter~=1.13
Requires-Dist: numpy~=1.26.4
Provides-Extra: dev
Requires-Dist: flake8>=7.2; extra == "dev"
Requires-Dist: flake8-docstrings>=1.7; extra == "dev"
Requires-Dist: black>=25.1; extra == "dev"
Requires-Dist: pytest>=8.3; extra == "dev"
Requires-Dist: parameterized>=0.9; extra == "dev"
Requires-Dist: sphinx>=7.0; extra == "dev"
Requires-Dist: sphinx_rtd_theme>=2.0; extra == "dev"
Requires-Dist: myst-parser>=2.0; extra == "dev"
Requires-Dist: sphinx-math-dollar>=1.2; extra == "dev"
Dynamic: license-file
